uma_api/__init__.py
uma_api/_version.py
uma_api/client.py
uma_api/constants.py
uma_api/events.py
uma_api/exceptions.py
uma_api/formatting.py
uma_api/mcp.py
uma_api/models.py
uma_api/py.typed
uma_api/websocket.py
uma_api-1.3.0.dist-info/licenses/LICENSE
uma_api-1.3.0.dist-info/METADATA
uma_api-1.3.0.dist-info/WHEEL
uma_api-1.3.0.dist-info/top_level.txt
uma_api-1.3.0.dist-info/RECORD
