Metadata-Version: 2.4
Name: uma-api
Version: 1.3.0
Summary: Python client library for the Unraid Management Agent API
Author-email: Ruaan Deysel <ruaan.deysel@example.com>
License-Expression: MIT
Project-URL: Homepage, https://github.com/ruaan-deysel/uma-api
Project-URL: Repository, https://github.com/ruaan-deysel/uma-api
Project-URL: Documentation, https://github.com/ruaan-deysel/uma-api#readme
Project-URL: Bug Tracker, https://github.com/ruaan-deysel/uma-api/issues
Keywords: unraid,api,client,monitoring,management
Classifier: Development Status :: 5 - Production/Stable
Classifier: Intended Audience :: Developers
Classifier: Programming Language :: Python :: 3
Classifier: Programming Language :: Python :: 3.12
Classifier: Programming Language :: Python :: 3.13
Classifier: Programming Language :: Python :: 3.14
Classifier: Operating System :: OS Independent
Classifier: Topic :: Software Development :: Libraries :: Python Modules
Classifier: Topic :: System :: Monitoring
Classifier: Topic :: Home Automation
Requires-Python: >=3.12
License-File: LICENSE
Requires-Dist: requests>=2.25.0
Requires-Dist: websockets>=10.0
Requires-Dist: pydantic>=2.0.0
Provides-Extra: async
Requires-Dist: aiohttp>=3.8.0; extra == "async"
Provides-Extra: dev
Requires-Dist: pytest>=7.0.0; extra == "dev"
Requires-Dist: pytest-cov>=3.0.0; extra == "dev"
Requires-Dist: pytest-asyncio>=0.21.0; extra == "dev"
Requires-Dist: aiohttp>=3.8.0; extra == "dev"
Requires-Dist: ruff>=0.8.0; extra == "dev"
Requires-Dist: mypy>=1.0.0; extra == "dev"
Requires-Dist: types-requests>=2.25.0; extra == "dev"
Requires-Dist: pre-commit>=3.0.0; extra == "dev"
Dynamic: license-file
